Workbook
Name beta_L: WACC_inputs!$B$11
Name beta_table: WACC_inputs!$B$17:$B$19
Name beta_U: WACC_inputs!$B$12
Name erp_base: WACC_inputs!$B$3
Name ke: WACC_inputs!$B$14
Name rf: WACC_inputs!$B$2
Name tax_rate: FCF_Sched!$I$1
Name wacc: WACC_inputs!$B$15

Sheet Drivers
A1: Line Item | B1: 2024 | C1: 2025 | D1: 2026 | E1: 2027 | F1: 2028
A2: # Customers (beginning) | B2: 1000 | C2: =B2*(1+C3) -> 1450 | D2: =C2*(1+D3) -> 1957.5 | E2: =D2*(1+E3) -> 2446.875 | F2: =E2*(1+F3) -> 2936.25 | H2: Blue Cells = Inputs
A3: Growth Rate (%) | B3: 0.6 | C3: 0.45 | D3: 0.35 | E3: 0.25 | F3: 0.2
A4: Average Revenue per Customer ($) | B4: 4000 | C4: =B4*(1+0.03) -> 4120 | D4: =C4*(1+0.03) -> 4243.6 | E4: =D4*(1+0.03) -> 4370.908 | F4: =E4*(1+0.03) -> 4502.0352
A5: Total Revenue (in $000´s) | B5: =B2*B4 -> 4000000 | C5: =C2*C4 -> 5974000 | D5: =D2*D4 -> 8306847 | E5: =E2*E4 -> 10695066 | F5: =F2*F4 -> 13219101
A7: A-col label | B7: 2024 | C7: 2025 | D7: 2026 | E7: 2027 | F7: 2028
A8: SG&A % of Revenue | B8: 0.25 | C8: =B8-0.01 -> 0.24 | D8: =C8-0.01 -> 0.23 | E8: =D8-0.01 -> 0.22 | F8: =E8-0.01 -> 0.21
A9: R&D % of Revenue | B9: 0.18 | C9: =B9-0.01 -> 0.17 | D9: =C9-0.01 -> 0.16 | E9: =D9-0.01 -> 0.15 | F9: =E9-0.01 -> 0.14
A11: DSO (days) | B11: 45 | C11: =B11-1 -> 44 | D11: =C11-1 -> 43 | E11: =D11-1 -> 42 | F11: =E11-1 -> 41
A12: DPO(days) | B12: 30 | C12: 30 | D12: 30 | E12: 30 | F12: 30

Sheet IncomeStmt
A1: Line Item | B1: 2024 | C1: 2025 | D1: 2026 | E1: 2027 | F1: 2028
A2: Revenue | B2: =Drivers!B5*FCF_Sched!$I9 -> 4000000 | C2: =Drivers!C5*FCF_Sched!$I9 -> 5974000 | D2: =Drivers!D5*FCF_Sched!$I9 -> 8306847 | E2: =Drivers!E5*FCF_Sched!$I9 -> 10695066 | F2: =Drivers!F5*FCF_Sched!$I9 -> 13219101 | H2: All Numbers in 000´s
A3: COGS | B3: =-B2*0.02 -> -80000 | C3: =-C2*0.02 -> -119480 | D3: =-D2*0.02 -> -166136.94 | E3: =-E2*0.02 -> -213901.31 | F3: =-F2*0.02 -> -264382.02
A4: Gross Profit | B4: =B2+B3 -> 3920000 | C4: =C2+C3 -> 5854520 | D4: =D2+D3 -> 8140710.1 | E4: =E2+E3 -> 10481164 | F4: =F2+F3 -> 12954719
A5: SG&A | B5: =-Drivers!B8*IncomeStmt!B$2 -> -1000000 | C5: =-Drivers!C8*IncomeStmt!C$2 -> -1433760 | D5: =-Drivers!D8*IncomeStmt!D$2 -> -1910574.8 | E5: =-Drivers!E8*IncomeStmt!E$2 -> -2352914.4 | F5: =-Drivers!F8*IncomeStmt!F$2 -> -2776011.2 | H5: Blue Cells = Inputs
A6: R&D | B6: =-Drivers!B$9*IncomeStmt!B$2 -> -720000 | C6: =-Drivers!C$9*IncomeStmt!C$2 -> -1015580 | D6: =-Drivers!D$9*IncomeStmt!D$2 -> -1329095.5 | E6: =-Drivers!E$9*IncomeStmt!E$2 -> -1604259.8 | F6: =-Drivers!F$9*IncomeStmt!F$2 -> -1850674.1
A7: EBIT | B7: =B4+B5+B6 -> 2200000 | C7: =C4+C5+C6 -> 3405180 | D7: =D4+D5+D6 -> 4901039.7 | E7: =E4+E5+E6 -> 6523990 | F7: =F4+F5+F6 -> 8328033.6
A8: Interest Expense | B8: 0 | C8: 0 | D8: 0 | E8: 0 | F8: 0
A9: Pre-Tax Income | B9: =B7-B8 -> 2200000 | C9: =C7-C8 -> 3405180 | D9: =D7-D8 -> 4901039.7 | E9: =E7-E8 -> 6523990 | F9: =F7-F8 -> 8328033.6
A10: Tax Expense | B10: =-FCF_Sched!B28 -> -550000 | C10: =-FCF_Sched!C28 -> -851295 | D10: =-FCF_Sched!D28 -> -1225259.9 | E10: =-FCF_Sched!E28 -> -1630997.5 | F10: =-FCF_Sched!F28 -> -2082008.4
A11: Net Income | B11: =B9+B10 -> 1650000 | C11: =C9+C10 -> 2553885 | D11: =D9+D10 -> 3675779.8 | E11: =E9+E10 -> 4892992.5 | F11: =F9+F10 -> 6246025.2

Sheet BalanceSheet
A1: Line Item | B1: 2024 | C1: 2025 | D1: 2026 | E1: 2027 | F1: 2028
A2: Cash | B2: 100000 | C2: =CashFlow!B14 -> 1526242.2 | D2: =CashFlow!C14 -> 3825500.6 | E2: =CashFlow!D14 -> 7253156 | F2: =CashFlow!E14 -> 11896077 | H2: All numbers in $000´s
A3: Accounts Receivable | B3: =IncomeStmt!B$2/365*Drivers!B$11 -> 493150.68 | C3: =IncomeStmt!C$2/365*Drivers!C$11 -> 720153.42 | D3: =IncomeStmt!D$2/365*Drivers!D$11 -> 978614.85 | E3: =IncomeStmt!E$2/365*Drivers!E$11 -> 1230665.1 | F3: =IncomeStmt!F$2/365*Drivers!F$11 -> 1484885.3
A4: Net PP&E | B4: 50000 | C4: 50000 | D4: 50000 | E4: 50000 | F4: 50000
A5: Total Assets | B5: =B2+B3+B4 -> 643150.68 | C5: =C2+C3+C4 -> 2296395.6 | D5: =D2+D3+D4 -> 4854115.4 | E5: =E2+E3+E4 -> 8533821.1 | F5: =F2+F3+F4 -> 13430963 | H5: Blue Cells = Inputs
A6: Accounts Payable | B6: =-(IncomeStmt!B$3/365)*Drivers!B$12 -> 6575.3425 | C6: =-(IncomeStmt!C$3/365)*Drivers!C$12 -> 9820.274 | D6: =-(IncomeStmt!D$3/365)*Drivers!D$12 -> 13655.091 | E6: =-(IncomeStmt!E$3/365)*Drivers!E$12 -> 17580.93 | F6: =-(IncomeStmt!F$3/365)*Drivers!F$12 -> 21730.029
A7: Long-Term Debt | B7: 0 | C7: 0 | D7: 0 | E7: 0 | F7: 0
A8: Common Equity | B8: =B5-B6-B7 -> 636575.34 | C8: =C5-C6-C7 -> 2286575.3 | D8: =D5-D6-D7 -> 4840460.3 | E8: =E5-E6-E7 -> 8516240.1 | F8: =F5-F6-F7 -> 13409233

Sheet CashFlow
A1: Line Item | B1: 2024 | C1: 2025 | D1: 2026 | E1: 2027 | F1: 2028
A2: Net Income | B2: =IncomeStmt!B11 -> 1650000 | C2: =IncomeStmt!C11 -> 2553885 | D2: =IncomeStmt!D11 -> 3675779.8 | E2: =IncomeStmt!E11 -> 4892992.5 | F2: =IncomeStmt!F11 -> 6246025.2 | H2: All numbers in $000´s
A3: Depreciation & Amortization | B3: 0 | C3: 0 | D3: 0 | E3: 0 | F3: 0
A4: ∆ Accounts Receivable | B4: =-1*(BalanceSheet!C3-BalanceSheet!B3) -> -227002.74 | C4: =-1*(BalanceSheet!D3-BalanceSheet!C3) -> -258461.43 | D4: =-1*(BalanceSheet!E3-BalanceSheet!D3) -> -252050.22 | E4: =-1*(BalanceSheet!F3-BalanceSheet!E3) -> -254220.24 | F4: =-1*(BalanceSheet!G3-BalanceSheet!F3) -> 1484885.3
A5: ∆ Accounts Payable | B5: =BalanceSheet!C6-BalanceSheet!B6 -> 3244.9315 | C5: =BalanceSheet!D6-BalanceSheet!C6 -> 3834.817 | D5: =BalanceSheet!E6-BalanceSheet!D6 -> 3925.8387 | E5: =BalanceSheet!F6-BalanceSheet!E6 -> 4149.0994 | F5: =BalanceSheet!G6-BalanceSheet!F6 -> -21730.029 | H5: Blue Cells = Inputs
A6: Operating Cash Flow | B6: =SUM(B2:B5) -> 1426242.2 | C6: =SUM(C2:C5) -> 2299258.4 | D6: =SUM(D2:D5) -> 3427655.4 | E6: =SUM(E2:E5) -> 4642921.3 | F6: =SUM(F2:F5) -> 7709180.5
A7: Capital Expenditures (CapEx) | B7: 0 | C7: 0 | D7: 0 | E7: 0 | F7: 0
A8: Investing Cash Flow | B8: =B7 -> 0 | C8: =C7 -> 0 | D8: =D7 -> 0 | E8: =E7 -> 0 | F8: =F7 -> 0
A9: Debt Issued (Repaid) | B9: 0 | C9: 0 | D9: 0 | E9: 0 | F9: 0
A10: Equity Issued | B10: 0 | C10: 0 | D10: 0 | E10: 0 | F10: 0
A11: Financing Cash Flow | B11: =B9+B10 -> 0 | C11: =C9+C10 -> 0 | D11: =D9+D10 -> 0 | E11: =E9+E10 -> 0 | F11: =F9+F10 -> 0
A12: Net Change in Cash | B12: =SUM(B6,B8,B11) -> 1426242.2 | C12: =SUM(C6,C8,C11) -> 2299258.4 | D12: =SUM(D6,D8,D11) -> 3427655.4 | E12: =SUM(E6,E8,E11) -> 4642921.3 | F12: =SUM(F6,F8,F11) -> 7709180.5
A13: Beggining Cash | B13: =BalanceSheet!B2 -> 100000 | C13: =BalanceSheet!C2 -> 1526242.2 | D13: =BalanceSheet!D2 -> 3825500.6 | E13: =BalanceSheet!E2 -> 7253156 | F13: =BalanceSheet!F2 -> 11896077
A14: Ending Cash | B14: =B13+B12 -> 1526242.2 | C14: =C13+C12 -> 3825500.6 | D14: =D13+D12 -> 7253156 | E14: =E13+E12 -> 11896077 | F14: =F13+F12 -> 19605258
A16: Free Cash Flow | B16: =B6-B7 -> 1426242.2 | C16: =C6-C7 -> 2299258.4 | D16: =D6-D7 -> 3427655.4 | E16: =E6-E7 -> 4642921.3 | F16: =F6-F7 -> 7709180.5

Sheet FCF_Sched
A1: Line Item | B1: 2024 | C1: 2025 | D1: 2026 | E1: 2027 | F1: 2028 | H1: Tax Rate | I1: 0.25
A2: EBIT | B2: =IncomeStmt!B7 -> 2200000 | C2: =IncomeStmt!C7 -> 3405180 | D2: =IncomeStmt!D7 -> 4901039.7 | E2: =IncomeStmt!E7 -> 6523990 | F2: =IncomeStmt!F7 -> 8328033.6
A3: Less: Cash tax | B3: =B28 -> 550000 | C3: =C28 -> 851295 | D3: =D28 -> 1225259.9 | E3: =E28 -> 1630997.5 | F3: =F28 -> 2082008.4 | H3: All numbers in $000´s
A4: Add: Depr. & Amort. | B4: =-IncomeStmt!B3 -> 80000 | C4: =-IncomeStmt!C3 -> 119480 | D4: =-IncomeStmt!D3 -> 166136.94 | E4: =-IncomeStmt!E3 -> 213901.31 | F4: =-IncomeStmt!F3 -> 264382.02
A5: Less: Capital Expenditures | B5: =IncomeStmt!B2*0.02 -> 80000 | C5: =IncomeStmt!C2*0.02 -> 119480 | D5: =IncomeStmt!D2*0.02 -> 166136.94 | E5: =IncomeStmt!E2*0.02 -> 213901.31 | F5: =IncomeStmt!F2*0.02 -> 264382.02
A6: Less: ∆ Net Working Capital | B6: =CashFlow!B4+CashFlow!B5 -> -223757.81 | C6: =CashFlow!C4+CashFlow!C5 -> -254626.61 | D6: =CashFlow!D4+CashFlow!D5 -> -248124.38 | E6: =CashFlow!E4+CashFlow!E5 -> -250071.14 | F6: =CashFlow!F4+CashFlow!F5 -> 1463155.3 | H6: Blue Cells = Inputs
A7: Unlevered FCF | B7: =B2-B3+B4-B5-B6 -> 1873757.8 | C7: =C2-C3+C4-C5-C6 -> 2808511.6 | D7: =D2-D3+D4-D5-D6 -> 3923904.2 | E7: =E2-E3+E4-E5-E6 -> 5143063.6 | F7: =F2-F3+F4-F5-F6 -> 4782869.9
A9: Sensititivity: Rev growth ±5% | H9: RevAdj | I9: 1
B10: =B7 -> 1873757.8 | C10: =C7 -> 2808511.6 | D10: =D7 -> 3923904.2 | E10: =E7 -> 5143063.6 | F10: =F7 -> 4782869.9
A11: 1.05 | B11: 1967445.7 | C11: 2948937.2 | D11: 4120099.4 | E11: 5400216.8 | F11: 5022013.4
A12: 1 | B12: 1873757.8 | C12: 2808511.6 | D12: 3923904.2 | E12: 5143063.6 | F12: 4782869.9
A13: 0.95 | B13: 1780069.9 | C13: 2668086 | D13: 3727709 | E13: 4885910.4 | F13: 4543726.4
B24: 2024 | C24: 2025 | D24: 2026 | E24: 2027 | F24: 2028
A25: Pre-Tax Income | B25: =IncomeStmt!B9 -> 2200000 | C25: =IncomeStmt!C9 -> 3405180 | D25: =IncomeStmt!D9 -> 4901039.7 | E25: =IncomeStmt!E9 -> 6523990 | F25: =IncomeStmt!F9 -> 8328033.6
A26: Beg. NOL | B26: =0 -> 0 | C26: =MAX(0, B30) -> 0 | D26: =MAX(0, C30) -> 0 | E26: =MAX(0, D30) -> 0 | F26: =MAX(0, E30) -> 0
A27: Taxable Income | B27: =MAX(0, B25-B26) -> 2200000 | C27: =MAX(0, C25-C26) -> 3405180 | D27: =MAX(0, D25-D26) -> 4901039.7 | E27: =MAX(0, E25-E26) -> 6523990 | F27: =MAX(0, F25-F26) -> 8328033.6
A28: Cash Tax @25% | B28: =B27*tax_rate -> 550000 | C28: =C27*tax_rate -> 851295 | D28: =D27*tax_rate -> 1225259.9 | E28: =E27*tax_rate -> 1630997.5 | F28: =F27*tax_rate -> 2082008.4
A29: NOL Used | B29: =B25-B27 -> 0 | C29: =C25-C27 -> 0 | D29: =D25-D27 -> 0 | E29: =E25-E27 -> 0 | F29: =F25-F27 -> 0
A30: End NOL | B30: =B26-B29+MIN(0, B28) -> 0 | C30: =C26-C29+MIN(0, C28) -> 0 | D30: =D26-D29+MIN(0, D28) -> 0 | E30: =E26-E29+MIN(0, E28) -> 0 | F30: =F26-F29+MIN(0, F28) -> 0

Sheet WACC_inputs
A2: Risk-free rate (Rf) | B2: 0.038
A3: Base ERP (US) | B3: 0.055
A4: Country default spread | B4: 0.1188
A5: Country equity risk premium | B5: 0.1602
A6: Corporate tax rate | B6: =tax_rate -> 0.25
A7: Debt/(Debt+Equity) | B7: 0
A8: Equity/(Debt+Equity) | B8: =1-B7 -> 1
A9: Cost of Debt (pre-tax) | B9: 0.14
A10: Cost of Debt (after-tax) | B10: =B9*(1-B6) -> 0.105
A11: Beta picker (levered) | B11: 1.3
A12: Unlevered β | B12: =B11/(1+(1-B6)*B7/B8) -> 1.3
A13: Re-levered β (target) | B13: =B12*(1+(1-B6)*B7/B8) -> 1.3
A14: Cost of equity (ke) | B14: =B2+B3*B13+B5 -> 0.2697
A15: WACC | B15: =B8*B14+B7*B10 -> 0.2697
B16: β
A17: SaaS 25th pct | B17: 0.8
A18: SaaS Median | B18: 1.05
A19: SaaS 75th pct | B19: 1.3

Sheet DCF
A1: Discounted Cash-Flow (DCF)
A3: WACC (%) | B3: =wacc -> 0.2697 | C3: =wacc -> 0.2697 | D3: =wacc -> 0.2697 | E3: =wacc -> 0.2697 | F3: =wacc -> 0.2697
A4: Terminal Growth (g) | B4: 0.03
A5: Free Cash Flow | B5: =FCF_Sched!B7 -> 1873757.8 | C5: =FCF_Sched!C7 -> 2808511.6 | D5: =FCF_Sched!D7 -> 3923904.2 | E5: =FCF_Sched!E7 -> 5143063.6 | F5: =FCF_Sched!F7 -> 4782869.9
A6: PV Factor | B6: =1/(1+$B$3)^(COLUMN()-COLUMN($B$3)) -> 1 | C6: =1/(1+$B$3)^(COLUMN()-COLUMN($B$3)) -> 0.78758762 | D6: =1/(1+$B$3)^(COLUMN()-COLUMN($B$3)) -> 0.62029426 | E6: =1/(1+$B$3)^(COLUMN()-COLUMN($B$3)) -> 0.48853608 | F6: =1/(1+$B$3)^(COLUMN()-COLUMN($B$3)) -> 0.38476497
A7: PV of FCF | B7: =B5*B6 -> 1873757.8 | C7: =C5*C6 -> 2211949 | D7: =D5*D6 -> 2433975.2 | E7: =E5*E6 -> 2512572.1 | F7: =F5*F6 -> 1840280.8
A8: Sum PV of forecast | B8: =SUM(B7:F7) -> 10872535
A9: Terminal Value (TV) | B9: =F5*(1+$B$4)/($B$3-$B$4) -> 20552174
A10: PV of TV | B10: =B9/((1+$B$3)^(COLUMN(F10)-COLUMN(B3)+1)) -> 6228051
A11: Enterprise Value (EV) | B11: =B8+B10 -> 17100586
A12: ="+Cash" -> +Cash | B12: =BalanceSheet!F2 -> 11896077
A13: ="-Debt" -> -Debt | B13: =BalanceSheet!F7 -> 0
A14: Equity Value | B14: =B11+B12-B13 -> 28996663
A15: Shares Outstanding (m) | B15: 10000000
A16: Implied share price | B16: =B14/B15 -> 2.8996663
