Workbook
Name base_decay: MonteCarlo!$C$3
Name base_growth: MonteCarlo!$C$2
Name base_margin: MonteCarlo!$C$4
Name base_wacc: MonteCarlo!$C$5
Name beta_L: WACC_inputs!$B$11
Name beta_table: WACC_inputs!$B$17:$B$19
Name beta_U: WACC_inputs!$B$12
Name current_price: DCF!$B$17
Name erp_base: WACC_inputs!$B$3
Name ev_per_share: DCF!$B$16
Name ke: WACC_inputs!$B$14
Name rf: WACC_inputs!$B$2
Name tax_rate: FCF_Sched!$I$1
Name wacc: WACC_inputs!$B$15

Sheet MonteCarlo
A1: Input | B1: Low | C1: Mode (Base) | D1: High | E1: Sample
A2: Growth Rate | B2: =base_growth-0.2 -> 0.4 | C2: 0.6 | D2: =base_growth+0.2 -> 0.8 | E2: =_xlfn.LET(_xlpm.a,B2, _xlpm.m,C2, _xlpm.b,D2, _xlpm.u,RAND(), IF(_xlpm.u<(_xlpm.m-_xlpm.a)/(_xlpm.b-_xlpm.a), _xlpm.a+SQRT(_xlpm.u*(_xlpm.b-_xlpm.a)*(_xlpm.m-_xlpm.a)), _xlpm.b-SQRT((1-_xlpm.u)*(_xlpm.b-_xlpm.a)*(_xlpm.b-_xlpm.m)))) -> 0.57489703 | G2: P10 | H2: =_xlfn.PERCENTILE.INC(B9:B1008, 0.1) -> 1.8728595 | J2: Monte-Carlo Toggle | K2: ON
A3: Decay Factor | B3: =C3-0.05 -> 0.7 | C3: 0.75 | D3: =C3+0.05 -> 0.8 | E3: =_xlfn.LET(_xlpm.a,B3, _xlpm.m,C3, _xlpm.b,D3, _xlpm.u,RAND(), IF(_xlpm.u<(_xlpm.m-_xlpm.a)/(_xlpm.b-_xlpm.a), _xlpm.a+SQRT(_xlpm.u*(_xlpm.b-_xlpm.a)*(_xlpm.m-_xlpm.a)), _xlpm.b-SQRT((1-_xlpm.u)*(_xlpm.b-_xlpm.a)*(_xlpm.b-_xlpm.m)))) -> 0.75208466 | G3: P50 | H3: =_xlfn.PERCENTILE.INC(B9:B1008, 0.5) -> 2.1352994
A4: Margin | B4: =base_margin-0.05 -> 0.22 | C4: 0.27 | D4: =base_margin+0.05 -> 0.32 | E4: =_xlfn.LET(_xlpm.a,B4, _xlpm.m,C4, _xlpm.b,D4, _xlpm.u,RAND(), IF(_xlpm.u<(_xlpm.m-_xlpm.a)/(_xlpm.b-_xlpm.a), _xlpm.a+SQRT(_xlpm.u*(_xlpm.b-_xlpm.a)*(_xlpm.m-_xlpm.a)), _xlpm.b-SQRT((1-_xlpm.u)*(_xlpm.b-_xlpm.a)*(_xlpm.b-_xlpm.m)))) -> 0.24019978 | G4: P90 | H4: =_xlfn.PERCENTILE.INC(B9:B1008, 0.9) -> 2.4515126
A5: WACC | C5: 0.2697 | D5: 0.015 | E5: =_xlfn.NORM.INV(RAND(),base_wacc,D5) -> 0.29254383 | G5: Prob > Current Price | H5: {=COUNTIF(B9:B1008, ">"&current_price)/1000} -> 0.741
A8: SimID | B8: =ev_per_share -> 1.8225037
A9: =ROW()-8 -> 1 | B9: 2.1147413
A10: =ROW()-8 -> 2 | B10: 2.3371318
A11: =ROW()-8 -> 3 | B11: 1.8947062
A12: =ROW()-8 -> 4 | B12: 2.4606856
A13: =ROW()-8 -> 5 | B13: 1.9036746
A14: =ROW()-8 -> 6 | B14: 1.9296293
A15: =ROW()-8 -> 7 | B15: 2.2123269
A16: =ROW()-8 -> 8 | B16: 2.1197592
A17: =ROW()-8 -> 9 | B17: 2.2520831
A18: =ROW()-8 -> 10 | B18: 1.9809272
A19: =ROW()-8 -> 11 | B19: 2.1086244
A20: =ROW()-8 -> 12 | B20: 2.2581385
... A1008: =ROW()-8 -> 1000 | B1008: 2.2092551

Sheet Drivers
A1: Line Item | B1: 2024 | C1: 2025 | D1: 2026 | E1: 2027 | F1: 2028
A2: # Customers (beginning) | B2: 1000 | C2: =B2*(1+C4) -> 1432.3712 | D2: =C2*(1+D4) -> 1898.1494 | E2: =D2*(1+E4) -> 2362.366 | F2: =E2*(1+F4) -> 2796.8803 | H2: Blue Cells = Inputs
A3: Decay Factor Growth | B3: =IF(MonteCarlo!$K$2="ON", MonteCarlo!E3, base_decay) -> 0.75208466
A4: Growth Rate (%) | B4: =IF(MonteCarlo!$K$2="ON", MonteCarlo!E2, base_growth) -> 0.57489703 | C4: =B4*$B$3 -> 0.43237124 | D4: =C4*$B$3 -> 0.32517977 | E4: =D4*$B$3 -> 0.24456272 | F4: =E4*$B$3 -> 0.18393187
A5: Average Revenue per Customer ($) | B5: 4000 | C5: =B5*(1+0.03) -> 4120 | D5: =C5*(1+0.03) -> 4243.6 | E5: =D5*(1+0.03) -> 4370.908 | F5: =E5*(1+0.03) -> 4502.0352 | H5: Green Cells = Dependent on MC
A6: Total Revenue (in $000´s) | B6: =B2*B5 -> 4000000 | C6: =C2*C5 -> 5901369.5 | D6: =D2*D5 -> 8054986.7 | E6: =E2*E5 -> 10325684 | F6: =F2*F5 -> 12591654
A8: A-col label | B8: 2024 | C8: 2025 | D8: 2026 | E8: 2027 | F8: 2028
A9: COGS % of Revenue | B9: 0.25 | C9: =$B$9 -> 0.25 | D9: =$B$9 -> 0.25 | E9: =$B$9 -> 0.25 | F9: =$B$9 -> 0.25
A10: SG&A % of Revenue | B10: 0.25 | C10: =$B$10 -> 0.25 | D10: =$B$10 -> 0.25 | E10: =$B$10 -> 0.25 | F10: =$B$10 -> 0.25
A11: R&D % of Revenue | B11: 0.18 | C11: =$B$11 -> 0.18 | D11: =$B$11 -> 0.18 | E11: =$B$11 -> 0.18 | F11: =$B$11 -> 0.18
A12: Target EBIT Margin | B12: =IF(MonteCarlo!$K$2="ON", MonteCarlo!E4, base_margin) -> 0.24019978 | C12: =$B$12 -> 0.24019978 | D12: =$B$12 -> 0.24019978 | E12: =$B$12 -> 0.24019978 | F12: =$B$12 -> 0.24019978
A14: DSO (days) | B14: 45 | C14: =B14-1 -> 44 | D14: =C14-1 -> 43 | E14: =D14-1 -> 42 | F14: =E14-1 -> 41
A15: DPO(days) | B15: 30 | C15: 30 | D15: 30 | E15: 30 | F15: 30

Sheet IncomeStmt
A1: Line Item | B1: 2024 | C1: 2025 | D1: 2026 | E1: 2027 | F1: 2028
A2: Revenue | B2: =Drivers!B6*FCF_Sched!$I9 -> 4000000 | C2: =Drivers!C6*FCF_Sched!$I9 -> 5901369.5 | D2: =Drivers!D6*FCF_Sched!$I9 -> 8054986.7 | E2: =Drivers!E6*FCF_Sched!$I9 -> 10325684 | F2: =Drivers!F6*FCF_Sched!$I9 -> 12591654 | H2: All Numbers in 000´s
A3: COGS | B3: =-B2*Drivers!B9 -> -1000000 | C3: =-C2*Drivers!C9 -> -1475342.4 | D3: =-D2*Drivers!D9 -> -2013746.7 | E3: =-E2*Drivers!E9 -> -2581421.1 | F3: =-F2*Drivers!F9 -> -3147913.5
A4: Gross Profit | B4: =B2+B3 -> 3000000 | C4: =C2+C3 -> 4426027.1 | D4: =D2+D3 -> 6041240.1 | E4: =E2+E3 -> 7744263.2 | F4: =F2+F3 -> 9443740.4
A5: SG&A | B5: =-Drivers!B10*IncomeStmt!B$2 -> -1000000 | C5: =-Drivers!C10*IncomeStmt!C$2 -> -1475342.4 | D5: =-Drivers!D10*IncomeStmt!D$2 -> -2013746.7 | E5: =-Drivers!E10*IncomeStmt!E$2 -> -2581421.1 | F5: =-Drivers!F10*IncomeStmt!F$2 -> -3147913.5 | H5: Blue Cells = Inputs
A6: R&D | B6: =-Drivers!B$11*IncomeStmt!B$2 -> -720000 | C6: =-Drivers!C$11*IncomeStmt!C$2 -> -1062246.5 | D6: =-Drivers!D$11*IncomeStmt!D$2 -> -1449897.6 | E6: =-Drivers!E$11*IncomeStmt!E$2 -> -1858623.2 | F6: =-Drivers!F$11*IncomeStmt!F$2 -> -2266497.7
A7: EBIT | B7: =B4+B5+B6 -> 1280000 | C7: =C4+C5+C6 -> 1888438.2 | D7: =D4+D5+D6 -> 2577595.8 | E7: =E4+E5+E6 -> 3304219 | F7: =F4+F5+F6 -> 4029329.2
A8: Adj EBIT | B8: =B2*Drivers!B12 -> 960799.1 | C8: =C2*Drivers!C12 -> 1417507.6 | D8: =D2*Drivers!D12 -> 1934806 | E8: =E2*Drivers!E12 -> 2480227 | F8: =F2*Drivers!F12 -> 3024512.4
A9: Actual EBIT | B9: =IF(MonteCarlo!$K$2="ON", B8, B7) -> 960799.1 | C9: =IF(MonteCarlo!$K$2="ON", C8, C7) -> 1417507.6 | D9: =IF(MonteCarlo!$K$2="ON", D8, D7) -> 1934806 | E9: =IF(MonteCarlo!$K$2="ON", E8, E7) -> 2480227 | F9: =IF(MonteCarlo!$K$2="ON", F8, F7) -> 3024512.4
A10: Interest Expense | B10: 0 | C10: 0 | D10: 0 | E10: 0 | F10: 0
A11: Pre-Tax Income | B11: =B9-B10 -> 960799.1 | C11: =C9-C10 -> 1417507.6 | D11: =D9-D10 -> 1934806 | E11: =E9-E10 -> 2480227 | F11: =F9-F10 -> 3024512.4
A12: Tax Expense | B12: =-FCF_Sched!B28 -> -240199.78 | C12: =-FCF_Sched!C28 -> -354376.91 | D12: =-FCF_Sched!D28 -> -483701.5 | E12: =-FCF_Sched!E28 -> -620056.76 | F12: =-FCF_Sched!F28 -> -756128.11
A13: Net Income | B13: =B11+B12 -> 720599.33 | C13: =C11+C12 -> 1063130.7 | D13: =D11+D12 -> 1451104.5 | E13: =E11+E12 -> 1860170.3 | F13: =F11+F12 -> 2268384.3

Sheet BalanceSheet
A1: Line Item | B1: 2024 | C1: 2025 | D1: 2026 | E1: 2027 | F1: 2028
A2: Cash | B2: 100000 | C2: =CashFlow!B14 -> 641421.28 | D2: =CashFlow!C14 -> 1511258.7 | E2: =CashFlow!D14 -> 2769804.1 | F2: =CashFlow!E14 -> 4450291.4 | H2: All numbers in $000´s
A3: Accounts Receivable | B3: =IncomeStmt!B$2/365*Drivers!B$14 -> 493150.68 | C3: =IncomeStmt!C$2/365*Drivers!C$14 -> 711397.97 | D3: =IncomeStmt!D$2/365*Drivers!D$14 -> 948943.64 | E3: =IncomeStmt!E$2/365*Drivers!E$14 -> 1188160.9 | F3: =IncomeStmt!F$2/365*Drivers!F$14 -> 1414405
A4: Net PP&E | B4: 50000 | C4: 50000 | D4: 50000 | E4: 50000 | F4: 50000
A5: Total Assets | B5: =B2+B3+B4 -> 643150.68 | C5: =C2+C3+C4 -> 1402819.2 | D5: =D2+D3+D4 -> 2510202.4 | E5: =E2+E3+E4 -> 4007965 | F5: =F2+F3+F4 -> 5914696.4 | H5: Blue Cells = Inputs
A6: Accounts Payable | B6: =-(IncomeStmt!B$3/365)*Drivers!B$15 -> 82191.781 | C6: =-(IncomeStmt!C$3/365)*Drivers!C$15 -> 121261.02 | D6: =-(IncomeStmt!D$3/365)*Drivers!D$15 -> 165513.43 | E6: =-(IncomeStmt!E$3/365)*Drivers!E$15 -> 212171.59 | F6: =-(IncomeStmt!F$3/365)*Drivers!F$15 -> 258732.61
A7: Long-Term Debt | B7: 0 | C7: 0 | D7: 0 | E7: 0 | F7: 0
A8: Common Equity | B8: =B5-B6-B7 -> 560958.9 | C8: =C5-C6-C7 -> 1281558.2 | D8: =D5-D6-D7 -> 2344688.9 | E8: =E5-E6-E7 -> 3795793.5 | F8: =F5-F6-F7 -> 5655963.7

Sheet CashFlow
A1: Line Item | B1: 2024 | C1: 2025 | D1: 2026 | E1: 2027 | F1: 2028
A2: Net Income | B2: =IncomeStmt!B13 -> 720599.33 | C2: =IncomeStmt!C13 -> 1063130.7 | D2: =IncomeStmt!D13 -> 1451104.5 | E2: =IncomeStmt!E13 -> 1860170.3 | F2: =IncomeStmt!F13 -> 2268384.3 | H2: All numbers in $000´s
A3: Depreciation & Amortization | B3: 0 | C3: 0 | D3: 0 | E3: 0 | F3: 0
A4: ∆ Accounts Receivable | B4: =-1*(BalanceSheet!C3-BalanceSheet!B3) -> -218247.28 | C4: =-1*(BalanceSheet!D3-BalanceSheet!C3) -> -237545.68 | D4: =-1*(BalanceSheet!E3-BalanceSheet!D3) -> -239217.29 | E4: =-1*(BalanceSheet!F3-BalanceSheet!E3) -> -226244.02 | F4: =-1*(BalanceSheet!G3-BalanceSheet!F3) -> 1414405
A5: ∆ Accounts Payable | B5: =BalanceSheet!C6-BalanceSheet!B6 -> 39069.236 | C5: =BalanceSheet!D6-BalanceSheet!C6 -> 44252.409 | D5: =BalanceSheet!E6-BalanceSheet!D6 -> 46658.169 | E5: =BalanceSheet!F6-BalanceSheet!E6 -> 46561.019 | F5: =BalanceSheet!G6-BalanceSheet!F6 -> -258732.61 | H5: Blue Cells = Inputs
A6: Operating Cash Flow | B6: =SUM(B2:B5) -> 541421.28 | C6: =SUM(C2:C5) -> 869837.45 | D6: =SUM(D2:D5) -> 1258545.4 | E6: =SUM(E2:E5) -> 1680487.3 | F6: =SUM(F2:F5) -> 3424056.7
A7: Capital Expenditures (CapEx) | B7: 0 | C7: 0 | D7: 0 | E7: 0 | F7: 0
A8: Investing Cash Flow | B8: =B7 -> 0 | C8: =C7 -> 0 | D8: =D7 -> 0 | E8: =E7 -> 0 | F8: =F7 -> 0
A9: Debt Issued (Repaid) | B9: 0 | C9: 0 | D9: 0 | E9: 0 | F9: 0
A10: Equity Issued | B10: 0 | C10: 0 | D10: 0 | E10: 0 | F10: 0
A11: Financing Cash Flow | B11: =B9+B10 -> 0 | C11: =C9+C10 -> 0 | D11: =D9+D10 -> 0 | E11: =E9+E10 -> 0 | F11: =F9+F10 -> 0
A12: Net Change in Cash | B12: =SUM(B6,B8,B11) -> 541421.28 | C12: =SUM(C6,C8,C11) -> 869837.45 | D12: =SUM(D6,D8,D11) -> 1258545.4 | E12: =SUM(E6,E8,E11) -> 1680487.3 | F12: =SUM(F6,F8,F11) -> 3424056.7
A13: Beggining Cash | B13: =BalanceSheet!B2 -> 100000 | C13: =BalanceSheet!C2 -> 641421.28 | D13: =BalanceSheet!D2 -> 1511258.7 | E13: =BalanceSheet!E2 -> 2769804.1 | F13: =BalanceSheet!F2 -> 4450291.4
A14: Ending Cash | B14: =B13+B12 -> 641421.28 | C14: =C13+C12 -> 1511258.7 | D14: =D13+D12 -> 2769804.1 | E14: =E13+E12 -> 4450291.4 | F14: =F13+F12 -> 7874348.1
A16: Free Cash Flow | B16: =B6-B7 -> 541421.28 | C16: =C6-C7 -> 869837.45 | D16: =D6-D7 -> 1258545.4 | E16: =E6-E7 -> 1680487.3 | F16: =F6-F7 -> 3424056.7

Sheet FCF_Sched
A1: Line Item | B1: 2024 | C1: 2025 | D1: 2026 | E1: 2027 | F1: 2028 | H1: Tax Rate | I1: 0.25
A2: EBIT | B2: =IncomeStmt!B9 -> 960799.1 | C2: =IncomeStmt!C9 -> 1417507.6 | D2: =IncomeStmt!D9 -> 1934806 | E2: =IncomeStmt!E9 -> 2480227 | F2: =IncomeStmt!F9 -> 3024512.4
A3: Less: Cash tax | B3: =B28 -> 240199.78 | C3: =C28 -> 354376.91 | D3: =D28 -> 483701.5 | E3: =E28 -> 620056.76 | F3: =F28 -> 756128.11 | H3: All numbers in $000´s
A4: Add: Depr. & Amort. | B4: =-IncomeStmt!B3 -> 1000000 | C4: =-IncomeStmt!C3 -> 1475342.4 | D4: =-IncomeStmt!D3 -> 2013746.7 | E4: =-IncomeStmt!E3 -> 2581421.1 | F4: =-IncomeStmt!F3 -> 3147913.5
A5: Less: Capital Expenditures | B5: =IncomeStmt!B2*0.02 -> 80000 | C5: =IncomeStmt!C2*0.02 -> 118027.39 | D5: =IncomeStmt!D2*0.02 -> 161099.73 | E5: =IncomeStmt!E2*0.02 -> 206513.69 | F5: =IncomeStmt!F2*0.02 -> 251833.08
A6: Less: ∆ Net Working Capital | B6: =CashFlow!B4+CashFlow!B5 -> -179178.05 | C6: =CashFlow!C4+CashFlow!C5 -> -193293.27 | D6: =CashFlow!D4+CashFlow!D5 -> -192559.12 | E6: =CashFlow!E4+CashFlow!E5 -> -179683.01 | F6: =CashFlow!F4+CashFlow!F5 -> 1155672.3 | H6: Blue Cells = Inputs
A7: Unlevered FCF | B7: =B2-B3+B4-B5-B6 -> 1819777.4 | C7: =C2-C3+C4-C5-C6 -> 2613739 | D7: =D2-D3+D4-D5-D6 -> 3496310.6 | E7: =E2-E3+E4-E5-E6 -> 4414760.7 | F7: =F2-F3+F4-F5-F6 -> 4008792.4
A9: Sensititivity: Rev growth ±5% | H9: RevAdj | I9: 1
B10: =B7 -> 1819777.4 | C10: =C7 -> 2613739 | D10: =D7 -> 3496310.6 | E10: =E7 -> 4414760.7 | F10: =F7 -> 4008792.4
A11: 1.05 | B11: 2041544.6 | C11: 2808031.4 | D11: 3613430.2 | E11: 4410896.2 | F11: 4020096.3
A12: 1 | B12: 1973730.6 | C12: 2830038.3 | D12: 3786545.3 | E12: 4788524 | F12: 4477434.3
A13: 0.95 | B13: 1901631.7 | C13: 2671334.8 | D13: 3511459.9 | E13: 4374374.8 | F13: 4074648.1
B24: 2024 | C24: 2025 | D24: 2026 | E24: 2027 | F24: 2028
A25: Pre-Tax Income | B25: =IncomeStmt!B11 -> 960799.1 | C25: =IncomeStmt!C11 -> 1417507.6 | D25: =IncomeStmt!D11 -> 1934806 | E25: =IncomeStmt!E11 -> 2480227 | F25: =IncomeStmt!F11 -> 3024512.4
A26: Beg. NOL | B26: =0 -> 0 | C26: =MAX(0, B30) -> 0 | D26: =MAX(0, C30) -> 0 | E26: =MAX(0, D30) -> 0 | F26: =MAX(0, E30) -> 0
A27: Taxable Income | B27: =MAX(0, B25-B26) -> 960799.1 | C27: =MAX(0, C25-C26) -> 1417507.6 | D27: =MAX(0, D25-D26) -> 1934806 | E27: =MAX(0, E25-E26) -> 2480227 | F27: =MAX(0, F25-F26) -> 3024512.4
A28: Cash Tax @25% | B28: =B27*tax_rate -> 240199.78 | C28: =C27*tax_rate -> 354376.91 | D28: =D27*tax_rate -> 483701.5 | E28: =E27*tax_rate -> 620056.76 | F28: =F27*tax_rate -> 756128.11
A29: NOL Used | B29: =B25-B27 -> 0 | C29: =C25-C27 -> 0 | D29: =D25-D27 -> 0 | E29: =E25-E27 -> 0 | F29: =F25-F27 -> 0
A30: End NOL | B30: =B26-B29+MIN(0, B28) -> 0 | C30: =C26-C29+MIN(0, C28) -> 0 | D30: =D26-D29+MIN(0, D28) -> 0 | E30: =E26-E29+MIN(0, E28) -> 0 | F30: =F26-F29+MIN(0, F28) -> 0

Sheet WACC_inputs
A2: Risk-free rate (Rf) | B2: 0.038
A3: Base ERP (US) | B3: 0.055
A4: Country default spread | B4: 0.1188
A5: Country equity risk premium | B5: 0.1602
A6: Corporate tax rate | B6: =tax_rate -> 0.25
A7: Debt/(Debt+Equity) | B7: 0
A8: Equity/(Debt+Equity) | B8: =1-B7 -> 1
A9: Cost of Debt (pre-tax) | B9: 0.14
A10: Cost of Debt (after-tax) | B10: =B9*(1-B6) -> 0.105
A11: Beta picker (levered) | B11: 1.3
A12: Unlevered β | B12: =B11/(1+(1-B6)*B7/B8) -> 1.3
A13: Re-levered β (target) | B13: =B12*(1+(1-B6)*B7/B8) -> 1.3
A14: Cost of equity (ke) | B14: =B2+B3*B13+B5 -> 0.2697
A15: WACC | B15: =IF(MonteCarlo!$K$2="ON", MonteCarlo!E5, base_wacc) -> 0.29254383 | C15: Estimated WACC | D15: =B8*B14+B7*B10 -> 0.2697
B16: β
A17: SaaS 25th pct | B17: 0.8
A18: SaaS Median | B18: 1.05
A19: SaaS 75th pct | B19: 1.3

Sheet DCF
A1: Discounted Cash-Flow (DCF)
A3: WACC (%) | B3: =wacc -> 0.29254383 | C3: =wacc -> 0.29254383 | D3: =wacc -> 0.29254383 | E3: =wacc -> 0.29254383 | F3: =wacc -> 0.29254383
A4: Terminal Growth (g) | B4: 0.03
A5: Free Cash Flow | B5: =FCF_Sched!B7 -> 1819777.4 | C5: =FCF_Sched!C7 -> 2613739 | D5: =FCF_Sched!D7 -> 3496310.6 | E5: =FCF_Sched!E7 -> 4414760.7 | F5: =FCF_Sched!F7 -> 4008792.4
A6: PV Factor | B6: =1/(1+$B$3)^(COLUMN()-COLUMN($B$3)) -> 1 | C6: =1/(1+$B$3)^(COLUMN()-COLUMN($B$3)) -> 0.77366815 | D6: =1/(1+$B$3)^(COLUMN()-COLUMN($B$3)) -> 0.59856241 | E6: =1/(1+$B$3)^(COLUMN()-COLUMN($B$3)) -> 0.46308867 | F6: =1/(1+$B$3)^(COLUMN()-COLUMN($B$3)) -> 0.35827696
A7: PV of FCF | B7: =B5*B6 -> 1819777.4 | C7: =C5*C6 -> 2022166.6 | D7: =D5*D6 -> 2092760.1 | E7: =E5*E6 -> 2044425.7 | F7: =F5*F6 -> 1436257.9
A8: Sum PV of forecast | B8: =SUM(B7:F7) -> 9415387.7
A9: Terminal Value (TV) | B9: =F5*(1+$B$4)/($B$3-$B$4) -> 15727111
A10: PV of TV | B10: =B9/((1+$B$3)^(COLUMN(F10)-COLUMN(B3)+1)) -> 4359358.3
A11: Enterprise Value (EV) | B11: =B8+B10 -> 13774746
A12: ="+Cash" -> +Cash | B12: =BalanceSheet!F2 -> 4450291.4
A13: ="-Debt" -> -Debt | B13: =BalanceSheet!F7 -> 0
A14: Equity Value | B14: =B11+B12-B13 -> 18225037
A15: Shares Outstanding (m) | B15: 10000000
A16: Implied share price | B16: =B14/B15 -> 1.8225037
A17: Current Price | B17: 2
